galaxy_test/__init__.py
galaxy_test/py.typed
galaxy_test/base/__init__.py
galaxy_test/base/api.py
galaxy_test/base/api_asserts.py
galaxy_test/base/api_util.py
galaxy_test/base/constants.py
galaxy_test/base/decorators.py
galaxy_test/base/env.py
galaxy_test/base/interactor.py
galaxy_test/base/json_schema_utils.py
galaxy_test/base/populators.py
galaxy_test/base/rules_test_data.py
galaxy_test/base/testcase.py
galaxy_test/base/uses_shed_api.py
galaxy_test/base/workflow_fixtures.py
galaxy_test/base/data/minimal_tool_no_id.json
galaxy_test/base/data/test_subworkflow_with_integer_input.ga
galaxy_test/base/data/test_subworkflow_with_tags.ga
galaxy_test/base/data/test_workflow_1.ga
galaxy_test/base/data/test_workflow_2.ga
galaxy_test/base/data/test_workflow_batch.ga
galaxy_test/base/data/test_workflow_map_reduce_pause.ga
galaxy_test/base/data/test_workflow_matching_lists.ga
galaxy_test/base/data/test_workflow_missing_tool.ga
galaxy_test/base/data/test_workflow_pause.ga
galaxy_test/base/data/test_workflow_randomlines_legacy_params.ga
galaxy_test/base/data/test_workflow_randomlines_legacy_params_mixed_types.ga
galaxy_test/base/data/test_workflow_topoambigouity.ga
galaxy_test/base/data/test_workflow_topoambigouity_auto_laidout.ga
galaxy_test/base/data/test_workflow_two_random_lines.ga
galaxy_test/base/data/test_workflow_validation_1.ga
galaxy_test/base/data/test_workflow_with_input_tags.ga
galaxy_test/base/data/test_workflow_with_runtime_input.ga
galaxy_test_base-25.0.3.dist-info/licenses/LICENSE
galaxy_test_base-25.0.3.dist-info/METADATA
galaxy_test_base-25.0.3.dist-info/WHEEL
galaxy_test_base-25.0.3.dist-info/top_level.txt
galaxy_test_base-25.0.3.dist-info/RECORD
